{"skeleton":{"hash":"mDcGlbkPw7g","spine":"4.1.23","x":-238.94,"y":-19.66,"width":414.06,"height":529.9,"images":"./images/","audio":"D:/character/ArmoredSkin"},"bones":[{"name":"root","y":0.32},{"name":"com","parent":"root","x":-0.71,"y":82.99},{"name":"Wolf_body","parent":"com","length":52.45,"rotation":88.31,"x":6.2,"y":46.53},{"name":"Wolf_body2","parent":"Wolf_body","length":67.98,"rotation":-0.4,"x":52.45},{"name":"Wolf_body3","parent":"Wolf_body2","length":62.06,"rotation":0.66,"x":67.98},{"name":"Wolf_arm_l","parent":"Wolf_body3","length":61.51,"rotation":-154.46,"x":37.79,"y":-42.75},{"name":"Wolf_arm_l2","parent":"Wolf_arm_l","length":49.73,"rotation":10.47,"x":61.51},{"name":"Wolf_arm_l3","parent":"Wolf_arm_l2","length":53.34,"rotation":8.3,"x":49.73},{"name":"weapon","parent":"Wolf_arm_l3","length":38.57,"rotation":68.56,"x":30.46,"y":-1.15},{"name":"Wolf_bag","parent":"Wolf_body","length":61.44,"rotation":-179.75,"x":60.53,"y":41.51},{"name":"Wolf_leg_r","parent":"Wolf_body","length":96,"rotation":168.24,"x":29,"y":26.62},{"name":"Wolf_leg_r2","parent":"Wolf_leg_r","length":48.91,"rotation":-7.74,"x":96},{"name":"Wolf_leg_r3","parent":"Wolf_leg_r2","length":35.56,"rotation":64.07,"x":48.91},{"name":"Wolf_leg_l","parent":"Wolf_body","length":87.69,"rotation":173.77,"x":34.54,"y":-45.22},{"name":"Wolf_leg_l2","parent":"Wolf_leg_l","length":59.98,"rotation":-12.66,"x":88.35,"y":-0.22},{"name":"Wolf_leg_l3","parent":"Wolf_leg_l2","length":41.07,"rotation":82.67,"x":59.69,"y":-0.11},{"name":"Wolf_tail","parent":"Wolf_body","length":37.04,"rotation":118.05,"x":8.55,"y":15.15},{"name":"Wolf_tail2","parent":"Wolf_tail","length":32.57,"rotation":-6.88,"x":37.04},{"name":"Wolf_tail3","parent":"Wolf_tail2","length":35.1,"rotation":-16.43,"x":32.86,"y":-0.1},{"name":"Wolf_tail4","parent":"Wolf_tail3","length":41.66,"rotation":-6.88,"x":36.03,"y":-0.05},{"name":"Wolf_tail5","parent":"Wolf_tail4","length":34.34,"rotation":-19.02,"x":41.97,"y":0.02},{"name":"Wolf_tail6","parent":"Wolf_tail5","length":77.56,"rotation":-18.74,"x":34.34},{"name":"Wolf_deco","parent":"Wolf_body3","length":71.72,"rotation":99.39,"x":50.77,"y":25},{"name":"Wolf_arm_r","parent":"Wolf_body3","length":79.45,"rotation":151.96,"x":36.12,"y":52.24},{"name":"Wolf_arm_r2","parent":"Wolf_arm_r","length":60.53,"rotation":11.87,"x":79.45},{"name":"Wolf_arm_r3","parent":"Wolf_arm_r2","length":42.03,"rotation":9.11,"x":60.53},{"name":"Wolf_head","parent":"Wolf_body3","length":148.94,"rotation":-3.53,"x":66.41,"y":20.5},{"name":"Wolf_eye","parent":"Wolf_head","x":78.95,"y":-59.49},{"name":"Wolf_head2","parent":"Wolf_head","x":14,"y":-81.92},{"name":"Wolf_head3","parent":"Wolf_head","x":30.43,"y":64.86},{"name":"Wolf_head4","parent":"Wolf_head","x":46.7,"y":-131.94},{"name":"Wolf_ear_r","parent":"Wolf_head","length":54.48,"rotation":37.22,"x":119.09,"y":24.11},{"name":"Wolf_ear_l","parent":"Wolf_head","length":33.21,"rotation":-43.05,"x":126.02,"y":-81},{"name":"Wolf_body4","parent":"Wolf_body2","x":0.46,"y":-63.1},{"name":"helmet","parent":"Wolf_head","rotation":-85.03,"x":77.67,"y":-34.59}],"slots":[{"name":"Wolf_arm_l","bone":"Wolf_arm_l","attachment":"Wolf_arm_l"},{"name":"weapon","bone":"weapon"},{"name":"Wolf_tail","bone":"Wolf_tail","attachment":"Wolf_tail"},{"name":"Wolf_leg_l","bone":"Wolf_leg_l","attachment":"Wolf_leg_l"},{"name":"Wolf_leg_r","bone":"Wolf_leg_r","attachment":"Wolf_leg_r"},{"name":"Wolf_body","bone":"Wolf_body","attachment":"Wolf_body"},{"name":"Wolf_bag","bone":"Wolf_bag","attachment":"Wolf_bag"},{"name":"Wolf_arm_r","bone":"Wolf_arm_r","attachment":"Wolf_arm_r"},{"name":"Wolf_deco","bone":"Wolf_deco","attachment":"Wolf_deco"},{"name":"Wolf_ear_l","bone":"Wolf_ear_l","attachment":"Wolf_ear_l"},{"name":"Wolf_head","bone":"Wolf_head","attachment":"Wolf_head"},{"name":"Wolf_ear_r","bone":"Wolf_ear_r","attachment":"Wolf_ear_r"},{"name":"Wolf_eye","bone":"Wolf_eye","attachment":"Wolf_eye"},{"name":"helmet","bone":"helmet"}],"skins":[{"name":"default","attachments":{"Wolf_arm_l":{"Wolf_arm_l":{"type":"mesh","uvs":[0.28273,0,0.48206,0.09992,0.52736,0.37942,0.64777,0.55032,1,0.69731,1,0.7618,0.88461,1,0.71087,1,0.49653,0.94505,0.36077,0.76576,0.18898,0.53889,0,0.28933,0.02378,0.09677],"triangles":[6,7,5,7,8,5,5,8,4,8,9,3,8,3,4,9,10,3,10,2,3,10,11,2,11,1,2,11,0,1,11,12,0],"vertices":[1,5,-18.38,24.7,1,2,5,10.89,44.13,0.99994,6,-41.75,52.6,6.0E-5,2,5,61.61,28.83,0.46584,6,5.34,28.33,0.53416,3,5,98.27,32.08,4.3E-4,6,41.98,24.86,0.64295,7,-4.09,25.72,0.35662,1,7,51.88,45.38,1,1,7,60.76,37.13,1,1,7,81.88,-5.94,1,1,7,64.26,-24.91,1,2,6,90.28,-35.81,0.00562,7,34.96,-41.29,0.99438,2,6,51.05,-33.33,0.46754,7,-3.5,-33.17,0.53246,2,5,68.38,-29.44,0.39378,6,1.41,-30.2,0.60622,1,5,14.06,-35.98,1,1,5,-17.54,-17.95,1],"hull":13,"edges":[0,2,2,4,4,6,6,8,8,10,10,12,12,14,14,16,16,18,6,18,8,16,10,14,18,20,20,22,4,20,22,2,24,0,22,24],"width":149,"height":188}},"Wolf_arm_r":{"Wolf_arm_r":{"type":"mesh","uvs":[0.97287,0.00425,1,0.18265,0.86938,0.36843,0.7452,0.49868,0.60345,0.64737,0.65139,0.76205,0.54852,1,0.38798,1,0,0.92813,0,0.80289,0.08085,0.63466,0.20254,0.38144,0.25383,0.27471,0.4386,0.0054],"triangles":[6,7,5,5,7,9,7,8,9,5,9,10,5,10,4,3,4,11,4,10,11,11,12,3,3,12,2,1,2,13,2,12,13,13,0,1],"vertices":[1,23,-18.58,12.36,1,1,23,10.92,32.7,1,2,23,50.85,37.55,0.8903,24,-20.27,42.63,0.1097,2,23,80.73,37.61,0.39345,24,8.99,36.54,0.60655,3,23,114.85,37.68,0.01285,24,42.39,29.59,0.78991,25,-13.22,32.09,0.19724,2,24,62.55,41.92,0.30882,25,8.63,41.07,0.69118,2,24,111.58,44.74,1.7E-4,25,57.49,36.09,0.99983,1,25,60.29,17.35,1,1,25,52.83,-30.05,1,2,24,93.57,-28.88,0.01493,25,28.06,-33.75,0.98507,2,24,58.62,-29.96,0.64491,25,-6.63,-29.28,0.35509,2,23,91.82,-29.67,0.31031,24,6,-31.58,0.68969,2,23,70.26,-34.9,0.82566,24,-16.18,-32.27,0.17434,1,23,12.64,-42.42,1],"hull":14,"edges":[0,26,0,2,8,10,10,12,12,14,14,16,16,18,18,20,20,8,18,10,10,14,20,22,6,8,22,6,22,24,4,6,24,4,24,26,26,2,2,4],"width":118,"height":200}},"Wolf_bag":{"Wolf_bag":{"x":41.65,"y":-2.56,"rotation":91.45,"width":162,"height":142}},"Wolf_body":{"Wolf_body":{"type":"mesh","uvs":[0.47484,0,0.89143,0.05848,0.90867,0.17578,0.92262,0.27071,0.94453,0.41979,0.97414,0.62126,1,0.79723,0.64224,1,0.37669,1,0,0.92502,0,0.84133,0.00955,0.64161,0.01882,0.44765,0.02533,0.31147,0.03016,0.21027,0.40707,0,0.71395,0.18343,0.7423,0.2789,0.75225,0.42557,0.76361,0.6257,0.74142,0.80863],"triangles":[19,18,4,19,4,5,20,11,19,6,20,19,6,19,5,7,20,6,16,0,1,16,1,2,16,14,15,16,15,0,17,16,2,17,2,3,13,14,16,13,16,17,18,17,3,18,3,4,13,17,18,12,13,18,19,11,12,19,12,18,10,11,20,8,9,10,20,8,10,7,8,20],"vertices":[2,4,78.29,-1.15,0.99962,33,145.82,62.85,3.8E-4,3,3,136.1,-67.74,0.00938,4,67.34,-68.52,0.92539,33,135.65,-4.64,0.06523,3,3,110.89,-71.43,0.052,4,42.08,-71.92,0.83433,33,110.43,-8.33,0.11367,3,3,90.48,-74.43,0.13394,4,21.64,-74.68,0.65733,33,90.02,-11.33,0.20874,3,3,58.43,-79.13,0.23322,4,-10.46,-79.01,0.30409,33,57.97,-16.03,0.46269,3,3,15.11,-85.48,0.04336,4,-53.85,-84.87,0.03104,33,14.66,-22.38,0.9256,3,2,29.09,-90.87,0.0551,4,-91.74,-89.98,0,33,-23.18,-27.93,0.9449,2,2,-16.39,-34.59,0.79975,33,-69.05,28.03,0.20025,2,2,-17.65,8.15,0.99938,33,-70.61,70.76,6.2E-4,2,2,-3.26,69.24,0.96694,3,-56.18,68.86,0.03306,2,2,14.81,69.78,0.92077,3,-38.12,69.52,0.07923,3,2,57.98,69.52,0.51182,3,5.05,69.56,0.46986,4,-62.12,70.28,0.01832,3,2,99.9,69.27,0.10871,3,46.97,69.59,0.67078,4,-20.2,69.83,0.22051,3,2,129.33,69.09,0.01512,3,76.4,69.62,0.46144,4,9.23,69.52,0.52343,3,2,151.2,68.96,0.00103,3,98.28,69.64,0.31082,4,31.1,69.29,0.68815,2,3,145.88,10.66,8.0E-5,4,78.02,9.76,0.99992,3,3,108.09,-40.16,0.03473,4,39.65,-40.62,0.89615,33,107.63,22.93,0.06912,3,3,87.65,-45.48,0.14257,4,19.15,-45.7,0.70995,33,87.19,17.62,0.14748,3,3,56.05,-48.24,0.37426,4,-12.49,-48.1,0.29232,33,55.59,14.86,0.33342,4,2,65,-51.73,0.01688,3,12.91,-51.64,0.22194,4,-55.65,-51,0.01879,33,12.46,11.46,0.74239,3,2,25.4,-49.33,0.3802,3,-26.7,-49.51,0.01175,33,-27.16,13.58,0.60805],"hull":16,"edges":[0,30,0,2,12,14,14,16,16,18,18,20,28,30,20,22,10,12,22,24,8,10,24,26,26,28,6,8,2,4,4,6,4,32,32,28,0,32,6,34,34,26,32,34,8,36,36,24,34,36,10,38,38,22,36,38,12,40,40,20,38,40,40,14],"width":161,"height":216}},"Wolf_deco":{"Wolf_deco":{"x":39.47,"y":8.95,"rotation":172.05,"width":127,"height":85}},"Wolf_ear_l":{"Wolf_ear_l":{"x":26.2,"y":2.02,"rotation":-41.99,"width":54,"height":89}},"Wolf_ear_r":{"Wolf_ear_r":{"x":28.36,"y":-6.42,"rotation":-122.25,"width":84,"height":90}},"Wolf_eye":{"Wolf_eye":{"x":0.29,"y":12.83,"rotation":-85.03,"width":148,"height":45}},"Wolf_head":{"Wolf_head":{"type":"mesh","uvs":[0.91823,0.22492,0.99855,0.49598,0.99357,0.662,0.88741,0.7907,0.84098,0.84699,0.71811,0.99596,0.53936,0.99838,0.41853,0.92989,0.28613,0.85484,0.06291,0.7283,0,0.56753,0,0.45834,0.20905,0.25187,0.46405,0,0.56978,0,0.8592,0.02569,0.52622,0.70149,0.71892,0.65107,0.84484,0.72434,0.48118,0.79701,0.731,0.79022,0.84321,0.77614,0.90526,0.5536,0.90526,0.69745,0.2394,0.59998,0.25302,0.75953,0.69157,0.4615],"triangles":[9,10,24,23,22,2,3,23,2,3,18,23,18,20,17,21,20,18,21,18,3,4,20,21,20,5,6,19,16,20,2,22,1,22,18,17,17,26,22,22,26,0,9,24,25,9,25,8,15,0,26,15,26,14,13,14,26,12,13,26,24,12,26,16,24,26,17,16,26,25,24,16,19,25,16,8,25,19,7,8,19,6,7,19,24,11,12,1,22,0,16,17,20,20,6,19,5,20,4,4,21,3,23,18,22,24,10,11],"vertices":[1,26,145.06,-117.47,1,2,26,85.16,-142.1,0.8893,30,38.46,-10.16,0.1107,3,26,47.35,-144.19,0.00158,28,33.35,-62.26,7.6E-4,30,0.65,-12.25,0.99767,3,26,15.9,-121.24,0.98857,28,1.9,-39.31,0.00618,30,-30.8,10.7,0.00525,1,26,2.14,-111.2,1,2,26,-34.25,-84.64,0.99714,28,-48.25,-2.71,0.00286,2,26,-38.53,-41.77,0.99714,28,-52.53,40.15,0.00286,1,26,-25.5,-11.41,1,1,26,-11.21,21.86,1,2,26,12.87,77.95,0.0062,29,-17.56,13.09,0.9938,2,26,48.08,96.23,0.03181,29,17.65,31.37,0.96819,2,26,72.88,98.39,0.77872,29,42.45,33.52,0.22128,2,26,124.14,52.27,0.99714,29,93.71,-12.59,0.00286,1,26,186.67,-3.99,1,2,26,188.88,-29.37,0.99143,30,142.18,102.57,0.00857,1,26,189.08,-99.37,1,1,26,28.63,-32.76,1,3,26,44.1,-78.03,0.99714,28,30.1,3.9,0.00198,30,-2.6,53.91,8.8E-4,1,26,30.08,-109.71,1,2,26,5.99,-23.83,0.99714,28,-8.01,58.1,0.00286,2,28,-1.25,-1.75,0.9912,30,-33.96,48.27,0.0088,3,26,18.29,-110.34,0.99714,28,4.29,-28.41,0.00183,30,-28.42,21.6,0.00103,1,26,70.13,-120.84,1,3,26,37.45,-123.68,0.99429,28,23.45,-41.76,0.00107,30,-9.25,8.26,0.00465,1,26,45.7,38.11,1,2,26,9.75,31.69,0.99714,29,-20.68,-33.17,0.00286,3,26,86.59,-67.72,0.98857,28,72.59,14.2,0.00359,30,39.89,64.22,0.00784],"hull":16,"edges":[2,4,10,12,18,20,20,22,26,28,28,30,12,14,32,34,34,36,8,10,14,38,38,32,38,40,8,42,42,36,40,42,40,10,40,12,2,0,0,30,0,44,44,46,4,6,6,8,46,6,22,24,24,26,24,48,18,50,50,38,48,50,14,16,16,18,50,16,22,48,48,18,48,52,52,34,52,44,52,28,52,24,52,0,52,30,34,40,40,36,40,32,32,52,32,48],"width":241,"height":228}},"Wolf_leg_l":{"Wolf_leg_l":{"type":"mesh","uvs":[1,0.21041,0.94629,0.51845,0.90742,0.74131,0.88629,0.86249,0.86814,0.96662,0.39407,0.99897,0.08092,0.85866,0.07696,0.74521,0.06933,0.52712,0.05846,0.21611,0.3403,0.01125,0.81449,0.00894],"triangles":[4,5,3,3,5,6,2,3,7,3,6,7,7,8,2,2,8,1,8,9,1,1,9,0,0,10,11,0,9,10],"vertices":[1,13,30.21,41.29,1,3,13,86.75,43.96,0.86465,14,-11.24,42.75,0.06066,15,33.46,75.82,0.07469,3,13,127.66,45.89,0.24392,14,28.25,53.6,0.1953,15,49.26,38.03,0.56079,3,13,149.9,46.94,0.05166,14,49.72,59.5,0.05491,15,57.85,17.49,0.89343,3,13,169.02,47.84,0.005,14,68.17,64.57,0.00158,15,65.24,-0.16,0.99341,1,15,27.8,-26.7,1,2,14,76.25,-13.12,0.24846,15,-10.79,-18.09,0.75154,2,14,56.95,-20.78,0.92614,15,-20.85,0.07,0.07386,2,13,99.94,-39.21,0.01141,14,19.85,-35.5,0.98859,2,13,43.71,-48.09,0.77396,14,-33.06,-56.49,0.22604,2,13,2.85,-26.47,0.99167,14,-77.67,-44.35,0.00833,1,13,-3.85,18.56,1],"hull":12,"edges":[8,10,10,12,18,20,20,22,12,14,14,4,4,6,6,8,12,6,14,16,16,18,0,2,2,4,16,2,18,0,22,0],"width":96,"height":183}},"Wolf_leg_r":{"Wolf_leg_r":{"type":"mesh","uvs":[1,0.07996,0.97023,0.22444,0.85474,0.54131,0.77392,0.76306,0.71928,0.91297,0.69942,0.96748,0.25031,0.98913,0.09074,0.92302,0.08546,0.77145,0.07753,0.54393,0.06649,0.22705,0.37584,0.0127,0.81318,0.00387],"triangles":[5,6,4,4,6,7,7,8,4,4,8,3,8,9,3,3,9,2,9,10,2,2,10,1,10,11,1,11,12,1,1,12,0],"vertices":[1,10,-3.99,33.07,1,1,10,23.82,36.66,1,3,10,85.99,39.66,0.67715,11,-15.27,37.95,0.28839,12,6.07,74.31,0.03446,3,10,129.49,41.75,0.0199,11,27.56,45.88,0.47611,12,31.93,39.26,0.50398,2,11,56.51,51.25,0.05787,12,49.42,15.57,0.94213,2,11,67.04,53.2,0.01254,12,55.77,6.95,0.98746,1,12,28.27,-28.8,1,1,12,8.07,-31.81,1,2,11,53.96,-17.72,0.44688,12,-13.73,-12.29,0.55312,2,10,104.56,-35.81,0.26232,11,13.3,-34.34,0.73768,2,10,45.33,-51.12,0.98032,11,-43.32,-57.48,0.01968,1,10,-2.1,-30.65,1,1,10,-13.93,11.48,1],"hull":13,"edges":[0,24,10,12,12,14,20,22,22,24,14,16,16,6,6,8,8,10,14,8,16,18,18,20,4,6,18,4,2,4,20,2,0,2,22,2],"width":100,"height":193}},"Wolf_tail":{"Wolf_tail":{"type":"mesh","uvs":[0.28613,0.12406,0.3972,0.24693,0.56344,0.43083,0.65741,0.32286,0.77358,0.33478,0.8686,0.34454,1,0.35803,1,0.42231,0.96274,0.59575,0.84478,0.78353,0.72987,0.96643,0.55489,0.97924,0.38978,0.99132,0.27115,1,0.19313,1,0.09192,0.79007,0,0.59941,0,0.39143,0.03032,0.08072,0.11167,0.04979,0.15167,0.03458,0.19155,0.01942],"triangles":[19,16,17,19,17,18,15,16,19,15,19,20,20,21,15,15,21,14,21,0,14,0,13,14,0,1,13,12,13,1,2,12,1,11,12,2,2,3,10,11,2,10,9,4,5,10,3,4,10,4,9,5,6,7,8,5,7,9,5,8],"vertices":[3,19,65.98,-46.71,0.03167,20,37.92,-36.36,0.30133,21,15.08,-33.28,0.66701,4,18,70.66,-42.17,0.00171,19,39.43,-37.67,0.34794,20,9.88,-36.46,0.54785,21,-11.45,-42.38,0.1025,4,17,57.58,-32.38,0.04835,18,32.83,-23.97,0.57798,19,-0.31,-24.13,0.35763,20,-32.1,-36.61,0.01604,3,17,33.77,-34.05,0.40386,18,10.47,-32.3,0.59363,19,-21.51,-35.08,0.00251,3,16,42.69,-24.9,0.10366,17,8.59,-24.04,0.80723,18,-16.51,-29.83,0.08911,3,16,23.23,-14.31,0.91425,17,-12,-15.86,0.08572,18,-38.57,-27.81,3.0E-5,1,16,-3.68,0.33,1,1,16,-1.18,5.4,1,1,16,13.37,15.23,1,2,16,45.34,17.85,0.20164,17,6.1,18.71,0.79836,2,17,36.71,24.98,0.51034,18,-3.41,25.14,0.48966,2,18,37.36,24.12,0.47354,19,-1.57,24.16,0.52646,3,19,36.74,27.81,0.75545,20,-14,24.57,0.24452,21,-53.66,7.74,3.0E-5,3,19,64.27,30.43,0.08293,20,11.17,36.02,0.80946,21,-33.51,26.67,0.1076,3,19,82.4,31.66,0.0028,20,27.92,43.08,0.67758,21,-19.92,38.74,0.31962,2,20,56.83,35.23,0.17139,21,9.98,40.59,0.82861,2,20,83.08,28.1,0.00312,21,37.14,42.27,0.99688,1,21,49.29,28.59,1,1,21,62.17,3.46,1,1,21,49.81,-11.17,1,2,20,69.85,-31.43,0.00365,21,43.73,-18.36,0.99635,3,19,88.58,-54.41,5.0E-5,20,61.81,-36.27,0.02471,21,37.67,-25.53,0.97525],"hull":22,"edges":[4,6,12,14,14,16,26,28,32,34,34,36,10,12,10,16,6,8,8,10,16,18,18,20,8,18,6,20,20,22,4,22,4,2,22,24,24,26,2,24,2,0,0,42,0,26,42,28,36,38,38,32,38,40,40,42,28,30,30,32,40,30],"width":233,"height":88}}}}],"events":{"event_attack":{}},"animations":{"attack":{"slots":{"weapon":{"rgba":[{"time":0.5333,"color":"ffffffff","curve":[0.578,1,0.622,1,0.578,1,0.622,1,0.578,1,0.622,1,0.578,0.67,0.622,0]},{"time":0.6667,"color":"ffffff00","curve":"stepped"},{"time":1.5333,"color":"ffffff00","curve":[1.578,1,1.622,1,1.578,1,1.622,1,1.578,1,1.622,1,1.578,0,1.622,1]},{"time":1.6667,"color":"ffffffff"}]},"Wolf_eye":{"rgba":[{"time":0.6667,"color":"ffffffff","curve":[0.678,1,0.689,1,0.678,1,0.689,1,0.678,1,0.689,1,0.678,0.67,0.689,0]},{"time":0.7,"color":"ffffff00","curve":"stepped"},{"time":0.7667,"color":"ffffff00","curve":[0.778,1,0.789,1,0.778,1,0.789,1,0.778,1,0.789,1,0.778,0,0.789,0.67]},{"time":0.8,"color":"ffffffff"}]}},"bones":{"Wolf_ear_l":{"rotate":[{"curve":[0.067,0,0.133,-7.67]},{"time":0.2,"value":-7.67,"curve":[0.222,-7.67,0.244,-2.17]},{"time":0.2667,"value":-2.17,"curve":[0.3,-2.17,0.333,-14.56]},{"time":0.3667,"value":-14.56,"curve":[0.4,-14.56,0.433,-3.65]},{"time":0.4667,"value":-3.65,"curve":[0.489,-3.65,0.511,-10.71]},{"time":0.5333,"value":-10.71,"curve":[0.567,-10.71,0.6,0.83]},{"time":0.6333,"value":0.83,"curve":[0.7,0.83,0.767,0.83]},{"time":0.8333,"curve":[0.889,-0.69,0.944,-10.66]},{"time":1,"value":-10.66,"curve":[1.089,-10.66,1.178,4.51]},{"time":1.2667,"value":4.51,"curve":[1.322,4.51,1.378,-15.22]},{"time":1.4333,"value":-15.22,"curve":[1.511,-15.22,1.589,0]},{"time":1.6667}]},"Wolf_ear_r":{"rotate":[{"curve":[0.067,0,0.133,-5.12]},{"time":0.2,"value":-5.12,"curve":[0.244,-5.12,0.289,4.5]},{"time":0.3333,"value":4.5,"curve":[0.367,4.5,0.4,-2.87]},{"time":0.4333,"value":-2.87,"curve":[0.467,-2.87,0.5,7.34]},{"time":0.5333,"value":7.34,"curve":[0.556,7.34,0.578,-2.79]},{"time":0.6,"value":-2.79,"curve":[0.644,-2.79,0.689,6.25]},{"time":0.7333,"value":6.25,"curve":[0.767,6.25,0.8,3.18]},{"time":0.8333,"value":2.42,"curve":[0.933,0.12,1.033,-2.92]},{"time":1.1333,"value":-2.92,"curve":[1.233,-2.92,1.333,8.26]},{"time":1.4333,"value":8.26,"curve":[1.511,8.26,1.589,0]},{"time":1.6667}]},"Wolf_head":{"rotate":[{"curve":[0.089,0,0.178,-8.94]},{"time":0.2667,"value":-8.88,"curve":[0.456,-8.76,0.644,0.76]},{"time":0.8333,"value":0.76,"curve":[0.922,0.76,1.011,-2.58]},{"time":1.1,"value":-2.68,"curve":[1.289,-2.9,1.478,0]},{"time":1.6667}],"translate":[{"curve":[0.279,0,0.557,-1.53,0.279,0,0.557,-13.83]},{"time":0.8333,"x":-1.96,"y":-14.91,"curve":[0.924,-2.1,1.478,0,0.924,-15.25,1.478,0]},{"time":1.6667}]},"Wolf_arm_r3":{"rotate":[{"curve":[0.278,0,0.556,-5.38]},{"time":0.8333,"value":-5.38,"curve":[1.111,-5.38,1.389,0]},{"time":1.6667}]},"Wolf_arm_r2":{"rotate":[{"curve":[0.089,0,0.178,26.69]},{"time":0.2667,"value":26.69,"curve":[0.456,26.69,0.644,-5.38]},{"time":0.8333,"value":-5.38,"curve":[1.111,-5.38,1.389,0]},{"time":1.6667}]},"Wolf_arm_r":{"rotate":[{"curve":[0.089,0,0.178,21.96]},{"time":0.2667,"value":21.96,"curve":[0.456,21.96,0.644,-24.58]},{"time":0.8333,"value":-24.58,"curve":[1.111,-24.58,1.389,0]},{"time":1.6667}]},"Wolf_deco":{"rotate":[{"curve":[0.278,0,0.556,-11.62]},{"time":0.8333,"value":-11.62,"curve":[1.111,-11.62,1.389,0]},{"time":1.6667}]},"Wolf_leg_l3":{"rotate":[{"curve":[0.278,0,0.556,3.81]},{"time":0.8333,"value":3.81,"curve":[1.111,3.81,1.389,0]},{"time":1.6667}]},"Wolf_leg_l2":{"rotate":[{"curve":[0.278,0,0.556,-4.76]},{"time":0.8333,"value":-4.76,"curve":[1.111,-4.76,1.389,0]},{"time":1.6667}]},"Wolf_leg_l":{"rotate":[{"curve":[0.278,0,0.556,13.68]},{"time":0.8333,"value":13.68,"curve":[1.111,13.68,1.389,0]},{"time":1.6667}]},"Wolf_leg_r3":{"rotate":[{"curve":[0.278,0,0.556,1.68]},{"time":0.8333,"value":1.68,"curve":[1.111,1.68,1.389,0]},{"time":1.6667}]},"Wolf_leg_r2":{"rotate":[{"curve":[0.278,0,0.556,-4.42]},{"time":0.8333,"value":-4.42,"curve":[1.111,-4.42,1.389,0]},{"time":1.6667}]},"Wolf_leg_r":{"rotate":[{"curve":[0.278,0,0.556,-3.39]},{"time":0.8333,"value":-3.39,"curve":[1.111,-3.39,1.389,0]},{"time":1.6667}]},"Wolf_bag":{"rotate":[{"curve":[0.144,0,0.289,-8.63]},{"time":0.4333,"value":-8.63,"curve":[0.567,-8.63,0.7,-2.43]},{"time":0.8333,"curve":[0.967,2.43,1.1,5.94]},{"time":1.2333,"value":5.94,"curve":[1.378,5.94,1.522,0]},{"time":1.6667}]},"Wolf_arm_l3":{"rotate":[{"curve":[0.278,0,0.556,3.56]},{"time":0.8333,"value":3.56,"curve":[1.111,3.56,1.389,0]},{"time":1.6667}]},"Wolf_arm_l2":{"rotate":[{"curve":[0.278,0,0.556,3.56]},{"time":0.8333,"value":3.56,"curve":[1.111,3.56,1.389,0]},{"time":1.6667}]},"Wolf_arm_l":{"rotate":[{"curve":[0.089,0,0.178,203.42]},{"time":0.2667,"value":203.42,"curve":[0.456,203.42,0.644,-44.94]},{"time":0.8333,"value":-44.94,"curve":[1.111,-44.94,1.389,0]},{"time":1.6667}]},"Wolf_body3":{"rotate":[{"curve":[0.089,0,0.178,3.81]},{"time":0.2667,"value":3.81,"curve":[0.456,3.81,0.644,-1.95]},{"time":0.8333,"value":-1.95,"curve":[0.9,-1.95,0.967,0.89]},{"time":1.0333,"value":0.89,"curve":[1.244,0.89,1.456,0]},{"time":1.6667}]},"Wolf_body2":{"rotate":[{"curve":[0.089,0,0.178,11.77]},{"time":0.2667,"value":11.77,"curve":[0.456,11.77,0.644,1.4]},{"time":0.8333,"value":1.4,"curve":[0.9,1.4,0.967,3.83]},{"time":1.0333,"value":3.83,"curve":[1.244,3.83,1.456,0]},{"time":1.6667}]},"Wolf_body":{"rotate":[{"curve":[0.089,0,0.178,2.94]},{"time":0.2667,"value":2.94,"curve":[0.456,2.94,0.644,-0.68]},{"time":0.8333,"value":-0.68,"curve":[1.111,-0.68,1.389,0]},{"time":1.6667}],"translate":[{"curve":[0.278,0,0.556,0.03,0.278,0,0.556,0.95]},{"time":0.8333,"x":0.03,"y":0.95,"curve":[1.111,0.03,1.389,0,1.111,0.95,1.389,0]},{"time":1.6667}],"scale":[{"curve":[0.278,1,0.556,1.028,0.278,1,0.556,1]},{"time":0.8333,"x":1.028,"curve":[1.111,1.028,1.389,1,1.111,1,1.389,1]},{"time":1.6667}]},"Wolf_head3":{"translate":[{"curve":[0.033,0,0.067,-3.93,0.033,0,0.067,6.06]},{"time":0.1,"x":-3.93,"y":6.06,"curve":[0.144,-3.93,0.189,-1.79,0.144,6.06,0.189,2.25]},{"time":0.2333,"x":-1.79,"y":2.25,"curve":[0.289,-1.79,0.344,-3.39,0.289,2.25,0.344,6.7]},{"time":0.4,"x":-3.39,"y":6.7,"curve":[0.456,-3.39,0.511,-3.17,0.456,6.7,0.511,3.65]},{"time":0.5667,"x":-2.6,"y":2.57,"curve":[0.622,-2.03,0.678,-0.69,0.622,1.49,0.678,0.22]},{"time":0.7333,"x":0.04,"y":0.22,"curve":[0.789,0.78,0.844,1.29,0.789,0.22,0.844,0.68]},{"time":0.9,"x":1.8,"y":1.42,"curve":[0.956,2.32,1.011,2.65,0.956,2.16,1.011,4.65]},{"time":1.0667,"x":3.14,"y":4.65,"curve":[1.122,3.62,1.178,4.73,1.122,4.65,1.178,1.69]},{"time":1.2333,"x":4.73,"y":1.69,"curve":[1.289,4.73,1.344,2.13,1.289,1.69,1.344,4.06]},{"time":1.4,"x":2.13,"y":4.06,"curve":[1.444,2.13,1.489,5.28,1.444,4.06,1.489,-2.22]},{"time":1.5333,"x":5.28,"y":-2.22,"curve":[1.578,5.28,1.622,0,1.578,-2.22,1.622,0]},{"time":1.6667}]},"Wolf_head4":{"translate":[{"curve":[0.044,0,0.089,-1.76,0.044,0,0.089,-2.1]},{"time":0.1333,"x":-1.76,"y":-2.1,"curve":[0.189,-1.76,0.244,-0.7,0.189,-2.1,0.244,-0.46]},{"time":0.3,"x":-0.41,"y":-0.46,"curve":[0.356,-0.11,0.411,-0.09,0.356,-0.46,0.411,-2.59]},{"time":0.4667,"x":0.01,"y":-2.59,"curve":[0.522,0.11,0.578,0.18,0.522,-2.59,0.578,0.03]},{"time":0.6333,"x":0.18,"y":0.03,"curve":[0.689,0.18,0.744,-1.05,0.689,0.03,0.744,-2.48]},{"time":0.8,"x":-1.05,"y":-2.48,"curve":[0.867,-1.05,0.933,-0.91,0.867,-2.48,0.933,0.35]},{"time":1,"x":-0.91,"y":0.35,"curve":[1.067,-0.91,1.133,-1.32,1.067,0.35,1.133,-2.07]},{"time":1.2,"x":-1.32,"y":-2.07,"curve":[1.267,-1.32,1.333,-0.34,1.267,-2.07,1.333,2.14]},{"time":1.4,"x":-0.19,"y":2.14,"curve":[1.489,0,1.578,0,1.489,2.14,1.578,0]},{"time":1.6667}]},"Wolf_head2":{"translate":[{"curve":[0.1,0,0.2,-3.75,0.1,0,0.2,-1.65]},{"time":0.3,"x":-3.75,"y":-1.65,"curve":[0.333,-3.75,0.367,-0.09,0.333,-1.65,0.367,-0.47]},{"time":0.4,"x":-0.09,"y":-0.47,"curve":[0.433,-0.09,0.467,-5.58,0.433,-0.47,0.467,-1.48]},{"time":0.5,"x":-5.58,"y":-1.84,"curve":[0.533,-5.58,0.567,-0.26,0.533,-2.2,0.567,-2.38]},{"time":0.6,"x":-0.26,"y":-2.62,"curve":[0.644,-0.26,0.689,-5.85,0.644,-2.95,0.689,-3.55]},{"time":0.7333,"x":-5.85,"y":-3.55,"curve":[0.789,-5.85,0.844,-2.52,0.789,-3.55,0.844,-3.21]},{"time":0.9,"x":-2.52,"y":-3.21,"curve":[0.989,-2.52,1.078,-6.06,0.989,-3.21,1.078,-5.34]},{"time":1.1667,"x":-6.06,"y":-5.34,"curve":[1.233,-6.06,1.3,-1.34,1.233,-5.34,1.3,-5.34]},{"time":1.3667,"x":-0.81,"y":-4.74,"curve":[1.467,0,1.567,0,1.467,-3.84,1.567,0]},{"time":1.6667}]},"Wolf_tail":{"rotate":[{"curve":[0.278,0,0.556,-0.33]},{"time":0.8333,"value":-0.33,"curve":[1.111,-0.33,1.389,0]},{"time":1.6667}]},"Wolf_tail2":{"rotate":[{"curve":[0.144,0,0.289,-7.44]},{"time":0.4333,"value":-7.44,"curve":[0.567,-7.44,0.7,-4]},{"time":0.8333,"value":-0.33,"curve":[0.967,3.35,1.1,14.61]},{"time":1.2333,"value":14.61,"curve":[1.378,14.61,1.522,0]},{"time":1.6667}]},"Wolf_tail3":{"rotate":[{"curve":[0.144,0,0.289,-7.44]},{"time":0.4333,"value":-7.44,"curve":[0.567,-7.44,0.7,-4]},{"time":0.8333,"value":-0.33,"curve":[0.967,3.35,1.1,14.61]},{"time":1.2333,"value":14.61,"curve":[1.378,14.61,1.522,0]},{"time":1.6667}]},"Wolf_tail4":{"rotate":[{"curve":[0.144,0,0.289,-7.44]},{"time":0.4333,"value":-7.44,"curve":[0.567,-7.44,0.7,-4]},{"time":0.8333,"value":-0.33,"curve":[0.967,3.35,1.1,14.61]},{"time":1.2333,"value":14.61,"curve":[1.378,14.61,1.522,0]},{"time":1.6667}]},"Wolf_tail5":{"rotate":[{"curve":[0.144,0,0.289,-7.44]},{"time":0.4333,"value":-7.44,"curve":[0.567,-7.44,0.7,-4]},{"time":0.8333,"value":-0.33,"curve":[0.967,3.35,1.1,14.61]},{"time":1.2333,"value":14.61,"curve":[1.378,14.61,1.522,0]},{"time":1.6667}]},"Wolf_tail6":{"rotate":[{"curve":[0.144,0,0.289,-7.44]},{"time":0.4333,"value":-7.44,"curve":[0.567,-7.44,0.7,-4]},{"time":0.8333,"value":-0.33,"curve":[0.967,3.35,1.1,14.61]},{"time":1.2333,"value":14.61,"curve":[1.378,14.61,1.522,0]},{"time":1.6667}]}},"events":[{"time":0.5333,"name":"event_attack"}]},"die":{"slots":{"Wolf_eye":{"rgba":[{"time":0.4,"color":"ffffffff"},{"time":0.4333,"color":"ffffff00"}]}},"bones":{"Wolf_ear_l":{"rotate":[{"curve":[0.047,0,0.087,-7.67]},{"time":0.1333,"value":-7.67,"curve":[0.149,-7.67,0.184,-2.17]},{"time":0.2,"value":-2.17,"curve":[0.223,-2.17,0.243,-14.56]},{"time":0.2667,"value":-14.56,"curve":[0.29,-14.56,0.31,-3.65]},{"time":0.3333,"value":-3.65,"curve":[0.349,-3.65,0.351,-10.71]},{"time":0.3667,"value":-10.71,"curve":[0.39,-10.71,0.41,0.83]},{"time":0.4333,"value":0.83,"curve":[0.48,0.83,0.553,0.83]},{"time":0.6,"curve":[0.639,-0.69,0.661,-10.66]},{"time":0.7,"value":-10.66,"curve":[0.762,-10.66,0.838,4.51]},{"time":0.9,"value":4.51,"curve":[0.939,4.51,0.961,-15.22]},{"time":1,"value":-15.22,"curve":[1.055,-15.22,1.112,0]},{"time":1.1667}]},"Wolf_ear_r":{"rotate":[{"curve":[0.047,0,0.087,-5.12]},{"time":0.1333,"value":-5.12,"curve":[0.164,-5.12,0.202,4.5]},{"time":0.2333,"value":4.5,"curve":[0.257,4.5,0.277,-2.87]},{"time":0.3,"value":-2.87,"curve":[0.323,-2.87,0.343,7.34]},{"time":0.3667,"value":7.34,"curve":[0.382,7.34,0.418,-2.79]},{"time":0.4333,"value":-2.79,"curve":[0.464,-2.79,0.469,6.25]},{"time":0.5,"value":6.25,"curve":[0.523,6.25,0.577,3.18]},{"time":0.6,"value":2.42,"curve":[0.67,0.12,0.73,-2.92]},{"time":0.8,"value":-2.92,"curve":[0.87,-2.92,0.93,8.26]},{"time":1,"value":8.26,"curve":[1.055,8.26,1.112,0]},{"time":1.1667}]},"Wolf_head":{"rotate":[{"curve":[0.195,0,0.405,0.4]},{"time":0.6,"value":0.4,"curve":[0.795,0.4,0.972,-27.04]},{"time":1.1667,"value":-27.04,"curve":[1.307,-27.04,1.46,9.43]},{"time":1.6,"value":9.43}],"translate":[{"x":0.57,"y":0.01,"curve":[0.257,0.57,0.51,-1.56,0.257,0.01,0.51,-3.9]},{"time":0.7667,"x":-1.56,"y":-3.9,"curve":[0.899,-1.56,1.034,0,0.899,-3.9,1.034,0]},{"time":1.1667}]},"Wolf_arm_r3":{"rotate":[{"curve":[0.195,0,0.405,-5.38]},{"time":0.6,"value":-5.38,"curve":[0.795,-5.38,0.972,0]},{"time":1.1667}]},"Wolf_arm_r2":{"rotate":[{"curve":[0.195,0,0.405,-5.38]},{"time":0.6,"value":-5.38,"curve":[0.795,-5.38,0.972,0]},{"time":1.1667}]},"Wolf_arm_r":{"rotate":[{"curve":[0.195,0,0.405,-5.38]},{"time":0.6,"value":-5.38,"curve":[0.795,-5.38,0.972,57.16]},{"time":1.1667,"value":57.16,"curve":[1.307,57.16,1.46,3.67]},{"time":1.6,"value":3.67}]},"Wolf_deco":{"rotate":[{"curve":[0.195,0,0.405,-11.62]},{"time":0.6,"value":-11.62,"curve":[0.795,-11.62,0.972,0]},{"time":1.1667}]},"Wolf_leg_l3":{"rotate":[{"curve":[0.195,0,0.405,3.81]},{"time":0.6,"value":3.81,"curve":[0.795,3.81,0.972,0]},{"time":1.1667}]},"Wolf_leg_l2":{"rotate":[{"curve":[0.195,0,0.405,-4.76]},{"time":0.6,"value":-4.76,"curve":[0.795,-4.76,0.972,0]},{"time":1.1667}]},"Wolf_leg_l":{"rotate":[{"curve":[0.195,0,0.405,1.85]},{"time":0.6,"value":1.85,"curve":[0.795,1.85,0.972,40.17]},{"time":1.1667,"value":40.17,"curve":[1.307,40.17,1.46,-27.95]},{"time":1.6,"value":-27.95}]},"Wolf_leg_r3":{"rotate":[{"curve":[0.195,0,0.405,1.68]},{"time":0.6,"value":1.68,"curve":[0.795,1.68,0.972,0]},{"time":1.1667}]},"Wolf_leg_r2":{"rotate":[{"curve":[0.195,0,0.405,-4.42]},{"time":0.6,"value":-4.42,"curve":[0.795,-4.42,0.972,0]},{"time":1.1667}]},"Wolf_leg_r":{"rotate":[{"curve":[0.195,0,0.405,2.45]},{"time":0.6,"value":2.45,"curve":[0.795,2.45,0.972,39.54]},{"time":1.1667,"value":39.54,"curve":[1.307,39.54,1.46,-3.99]},{"time":1.6,"value":-3.99}]},"Wolf_bag":{"rotate":[{"curve":[0.101,0,0.199,-8.63]},{"time":0.3,"value":-8.63,"curve":[0.393,-8.63,0.507,-2.43]},{"time":0.6,"curve":[0.693,2.43,0.773,5.94]},{"time":0.8667,"value":5.94,"curve":[0.968,5.94,1.065,0]},{"time":1.1667}]},"Wolf_arm_l3":{"rotate":[{"curve":[0.195,0,0.405,3.56]},{"time":0.6,"value":3.56,"curve":[0.795,3.56,0.972,0]},{"time":1.1667}]},"Wolf_arm_l2":{"rotate":[{"curve":[0.195,0,0.405,3.56]},{"time":0.6,"value":3.56,"curve":[0.795,3.56,0.972,0]},{"time":1.1667}]},"Wolf_arm_l":{"rotate":[{"curve":[0.195,0,0.405,3.56]},{"time":0.6,"value":3.56,"curve":[0.795,3.56,0.972,20.62]},{"time":1.1667,"value":20.62,"curve":[1.307,20.62,1.46,-39.63]},{"time":1.6,"value":-39.63}]},"Wolf_body3":{"rotate":[{"curve":[0.195,0,0.405,-1.95]},{"time":0.6,"value":-1.95,"curve":[0.795,-1.95,0.972,0]},{"time":1.1667}]},"Wolf_body2":{"rotate":[{"curve":[0.195,0,0.405,1.4]},{"time":0.6,"value":1.4,"curve":[0.795,1.4,0.972,0]},{"time":1.1667,"curve":[1.307,0,1.46,10.91]},{"time":1.6,"value":10.91}]},"Wolf_body":{"rotate":[{"curve":[0.195,0,0.405,-0.68]},{"time":0.6,"value":-0.68,"curve":[0.795,-0.68,0.972,0]},{"time":1.1667}],"translate":[{"curve":[0.195,0,0.405,0.03,0.195,0,0.405,0.95]},{"time":0.6,"x":0.03,"y":0.95,"curve":[0.795,0.03,0.972,0,0.795,0.95,0.972,0]},{"time":1.1667}],"scale":[{"curve":[0.195,1,0.405,1.028,0.195,1,0.405,1]},{"time":0.6,"x":1.028,"curve":[0.795,1.028,0.972,1,0.795,1,0.972,1]},{"time":1.1667}]},"Wolf_head3":{"translate":[{},{"time":0.0667,"x":-3.93,"y":6.06},{"time":0.1667,"x":-1.79,"y":2.25},{"time":0.2667,"x":-3.39,"y":6.7},{"time":0.4,"x":-2.6,"y":2.57},{"time":0.5,"x":0.04,"y":0.22},{"time":0.6333,"x":1.8,"y":1.42},{"time":0.7333,"x":3.14,"y":4.65},{"time":0.8667,"x":4.73,"y":1.69},{"time":0.9667,"x":2.13,"y":4.06},{"time":1.0667,"x":5.28,"y":-2.22},{"time":1.1667}]},"Wolf_head4":{"translate":[{},{"time":0.1,"x":-1.76,"y":-2.1},{"time":0.2,"x":-0.41,"y":-0.46},{"time":0.3333,"x":0.01,"y":-2.59},{"time":0.4333,"x":0.18,"y":0.03},{"time":0.5667,"x":-1.05,"y":-2.48},{"time":0.7,"x":-0.91,"y":0.35},{"time":0.8333,"x":-1.32,"y":-2.07},{"time":0.9667,"x":-0.19,"y":2.14},{"time":1.1667}]},"Wolf_head2":{"translate":[{},{"time":0.2,"x":-3.75,"y":-1.65},{"time":0.2667,"x":-0.09,"y":-0.47},{"time":0.3667,"x":-5.58,"y":-1.84},{"time":0.4333,"x":-0.26,"y":-2.62},{"time":0.5,"x":-5.85,"y":-3.55},{"time":0.6333,"x":-2.52,"y":-3.21},{"time":0.8333,"x":-6.06,"y":-5.34},{"time":0.9667,"x":-0.81,"y":-4.74},{"time":1.1667}]},"Wolf_tail":{"rotate":[{},{"time":0.6,"value":-0.33},{"time":1.1667,"value":20.73},{"time":1.6,"value":28.95}]},"Wolf_tail2":{"rotate":[{},{"time":0.3,"value":-7.44},{"time":0.6,"value":-0.33},{"time":0.8667,"value":14.61},{"time":1.1667,"value":20.73},{"time":1.6,"value":28.95}]},"Wolf_tail3":{"rotate":[{},{"time":0.3,"value":-7.44},{"time":0.6,"value":-0.33},{"time":0.8667,"value":14.61},{"time":1.1667,"value":20.73},{"time":1.6,"value":28.95}]},"Wolf_tail4":{"rotate":[{},{"time":0.3,"value":-7.44},{"time":0.6,"value":-0.33},{"time":0.8667,"value":14.61},{"time":1.1667,"value":20.73},{"time":1.6,"value":28.95}]},"Wolf_tail5":{"rotate":[{},{"time":0.3,"value":-7.44},{"time":0.6,"value":-0.33},{"time":0.8667,"value":14.61},{"time":1.1667,"value":20.73},{"time":1.6,"value":28.95}]},"Wolf_tail6":{"rotate":[{},{"time":0.3,"value":-7.44},{"time":0.6,"value":-0.33},{"time":0.8667,"value":14.61},{"time":1.1667,"value":20.73},{"time":1.6,"value":28.95}]},"com":{"rotate":[{},{"time":1.1667,"value":91.4}],"translate":[{},{"time":1.1667,"x":32.54,"y":-42.23},{"time":1.6,"x":46.16,"y":1.46},{"time":2,"x":69.42,"y":-45.06}]}}},"idle":{"slots":{"Wolf_eye":{"rgba":[{"time":0.6667,"color":"ffffffff"},{"time":0.7,"color":"ffffff00","curve":"stepped"},{"time":0.7667,"color":"ffffff00"},{"time":0.8,"color":"ffffffff"}]}},"bones":{"Wolf_ear_l":{"rotate":[{"curve":[0.067,0,0.133,-7.67]},{"time":0.2,"value":-7.67,"curve":[0.222,-7.67,0.244,-2.17]},{"time":0.2667,"value":-2.17,"curve":[0.3,-2.17,0.333,-14.56]},{"time":0.3667,"value":-14.56,"curve":[0.4,-14.56,0.433,-3.65]},{"time":0.4667,"value":-3.65,"curve":[0.489,-3.65,0.511,-10.71]},{"time":0.5333,"value":-10.71,"curve":[0.567,-10.71,0.6,0.83]},{"time":0.6333,"value":0.83,"curve":[0.7,0.83,0.767,0.83]},{"time":0.8333,"curve":[0.889,-0.69,0.944,-10.66]},{"time":1,"value":-10.66,"curve":[1.089,-10.66,1.178,4.51]},{"time":1.2667,"value":4.51,"curve":[1.322,4.51,1.378,-15.22]},{"time":1.4333,"value":-15.22,"curve":[1.511,-15.22,1.589,0]},{"time":1.6667}]},"Wolf_ear_r":{"rotate":[{"curve":[0.067,0,0.133,-5.12]},{"time":0.2,"value":-5.12,"curve":[0.244,-5.12,0.289,4.5]},{"time":0.3333,"value":4.5,"curve":[0.367,4.5,0.4,-2.87]},{"time":0.4333,"value":-2.87,"curve":[0.467,-2.87,0.5,7.34]},{"time":0.5333,"value":7.34,"curve":[0.556,7.34,0.578,-2.79]},{"time":0.6,"value":-2.79,"curve":[0.644,-2.79,0.689,6.25]},{"time":0.7333,"value":6.25,"curve":[0.767,6.25,0.8,3.18]},{"time":0.8333,"value":2.42,"curve":[0.933,0.12,1.033,-2.92]},{"time":1.1333,"value":-2.92,"curve":[1.233,-2.92,1.333,8.26]},{"time":1.4333,"value":8.26,"curve":[1.511,8.26,1.589,0]},{"time":1.6667}]},"Wolf_head":{"rotate":[{"curve":[0.278,0,0.556,0.4]},{"time":0.8333,"value":0.4,"curve":[1.111,0.4,1.389,0]},{"time":1.6667}],"translate":[{"x":0.57,"y":0.01,"curve":[0.367,0.57,0.733,-1.56,0.367,0.01,0.733,-3.9]},{"time":1.1,"x":-1.56,"y":-3.9,"curve":[1.289,-1.56,1.478,0,1.289,-3.9,1.478,0]},{"time":1.6667}]},"Wolf_arm_r3":{"rotate":[{"curve":[0.278,0,0.556,-5.38]},{"time":0.8333,"value":-5.38,"curve":[1.111,-5.38,1.389,0]},{"time":1.6667}]},"Wolf_arm_r2":{"rotate":[{"curve":[0.278,0,0.556,-5.38]},{"time":0.8333,"value":-5.38,"curve":[1.111,-5.38,1.389,0]},{"time":1.6667}]},"Wolf_arm_r":{"rotate":[{"curve":[0.278,0,0.556,-5.38]},{"time":0.8333,"value":-5.38,"curve":[1.111,-5.38,1.389,0]},{"time":1.6667}]},"Wolf_deco":{"rotate":[{"curve":[0.278,0,0.556,-11.62]},{"time":0.8333,"value":-11.62,"curve":[1.111,-11.62,1.389,0]},{"time":1.6667}]},"Wolf_leg_l3":{"rotate":[{"curve":[0.278,0,0.556,3.81]},{"time":0.8333,"value":3.81,"curve":[1.111,3.81,1.389,0]},{"time":1.6667}]},"Wolf_leg_l2":{"rotate":[{"curve":[0.278,0,0.556,-4.76]},{"time":0.8333,"value":-4.76,"curve":[1.111,-4.76,1.389,0]},{"time":1.6667}]},"Wolf_leg_l":{"rotate":[{"curve":[0.278,0,0.556,1.85]},{"time":0.8333,"value":1.85,"curve":[1.111,1.85,1.389,0]},{"time":1.6667}]},"Wolf_leg_r3":{"rotate":[{"curve":[0.278,0,0.556,1.68]},{"time":0.8333,"value":1.68,"curve":[1.111,1.68,1.389,0]},{"time":1.6667}]},"Wolf_leg_r2":{"rotate":[{"curve":[0.278,0,0.556,-4.42]},{"time":0.8333,"value":-4.42,"curve":[1.111,-4.42,1.389,0]},{"time":1.6667}]},"Wolf_leg_r":{"rotate":[{"curve":[0.278,0,0.556,2.45]},{"time":0.8333,"value":2.45,"curve":[1.111,2.45,1.389,0]},{"time":1.6667}]},"Wolf_bag":{"rotate":[{"curve":[0.144,0,0.289,-8.63]},{"time":0.4333,"value":-8.63,"curve":[0.567,-8.63,0.7,-2.43]},{"time":0.8333,"curve":[0.967,2.43,1.1,5.94]},{"time":1.2333,"value":5.94,"curve":[1.378,5.94,1.522,0]},{"time":1.6667}]},"Wolf_arm_l3":{"rotate":[{"curve":[0.278,0,0.556,3.56]},{"time":0.8333,"value":3.56,"curve":[1.111,3.56,1.389,0]},{"time":1.6667}]},"Wolf_arm_l2":{"rotate":[{"curve":[0.278,0,0.556,3.56]},{"time":0.8333,"value":3.56,"curve":[1.111,3.56,1.389,0]},{"time":1.6667}]},"Wolf_arm_l":{"rotate":[{"curve":[0.278,0,0.556,3.56]},{"time":0.8333,"value":3.56,"curve":[1.111,3.56,1.389,0]},{"time":1.6667}]},"Wolf_body3":{"rotate":[{"curve":[0.278,0,0.556,-1.95]},{"time":0.8333,"value":-1.95,"curve":[1.111,-1.95,1.389,0]},{"time":1.6667}]},"Wolf_body2":{"rotate":[{"curve":[0.278,0,0.556,1.4]},{"time":0.8333,"value":1.4,"curve":[1.111,1.4,1.389,0]},{"time":1.6667}]},"Wolf_body":{"rotate":[{"curve":[0.278,0,0.556,-0.68]},{"time":0.8333,"value":-0.68,"curve":[1.111,-0.68,1.389,0]},{"time":1.6667}],"translate":[{"curve":[0.278,0,0.556,0.03,0.278,0,0.556,0.95]},{"time":0.8333,"x":0.03,"y":0.95,"curve":[1.111,0.03,1.389,0,1.111,0.95,1.389,0]},{"time":1.6667}],"scale":[{"curve":[0.278,1,0.556,1.028,0.278,1,0.556,1]},{"time":0.8333,"x":1.028,"curve":[1.111,1.028,1.389,1,1.111,1,1.389,1]},{"time":1.6667}]},"Wolf_head3":{"translate":[{},{"time":0.1,"x":-3.93,"y":6.06},{"time":0.2333,"x":-1.79,"y":2.25},{"time":0.4,"x":-3.39,"y":6.7},{"time":0.5667,"x":-2.6,"y":2.57},{"time":0.7333,"x":0.04,"y":0.22},{"time":0.9,"x":1.8,"y":1.42},{"time":1.0667,"x":3.14,"y":4.65},{"time":1.2333,"x":4.73,"y":1.69},{"time":1.4,"x":2.13,"y":4.06},{"time":1.5333,"x":5.28,"y":-2.22},{"time":1.6667}]},"Wolf_head4":{"translate":[{},{"time":0.1333,"x":-1.76,"y":-2.1},{"time":0.3,"x":-0.41,"y":-0.46},{"time":0.4667,"x":0.01,"y":-2.59},{"time":0.6333,"x":0.18,"y":0.03},{"time":0.8,"x":-1.05,"y":-2.48},{"time":1,"x":-0.91,"y":0.35},{"time":1.2,"x":-1.32,"y":-2.07},{"time":1.4,"x":-0.19,"y":2.14},{"time":1.6667}]},"Wolf_head2":{"translate":[{},{"time":0.3,"x":-3.75,"y":-1.65},{"time":0.4,"x":-0.09,"y":-0.47},{"time":0.5,"x":-5.58,"y":-1.84},{"time":0.6,"x":-0.26,"y":-2.62},{"time":0.7333,"x":-5.85,"y":-3.55},{"time":0.9,"x":-2.52,"y":-3.21},{"time":1.1667,"x":-6.06,"y":-5.34},{"time":1.3667,"x":-0.81,"y":-4.74},{"time":1.6667}]},"Wolf_tail":{"rotate":[{},{"time":0.8333,"value":-0.33},{"time":1.6667}]},"Wolf_tail2":{"rotate":[{},{"time":0.4333,"value":-7.44},{"time":0.8333,"value":-0.33},{"time":1.2333,"value":14.61},{"time":1.6667}]},"Wolf_tail3":{"rotate":[{},{"time":0.4333,"value":-7.44},{"time":0.8333,"value":-0.33},{"time":1.2333,"value":14.61},{"time":1.6667}]},"Wolf_tail4":{"rotate":[{},{"time":0.4333,"value":-7.44},{"time":0.8333,"value":-0.33},{"time":1.2333,"value":14.61},{"time":1.6667}]},"Wolf_tail5":{"rotate":[{},{"time":0.4333,"value":-7.44},{"time":0.8333,"value":-0.33},{"time":1.2333,"value":14.61},{"time":1.6667}]},"Wolf_tail6":{"rotate":[{},{"time":0.4333,"value":-7.44},{"time":0.8333,"value":-0.33},{"time":1.2333,"value":14.61},{"time":1.6667}]}}},"run":{"slots":{"Wolf_eye":{"rgba":[{"time":0.6667,"color":"ffffffff"},{"time":0.7,"color":"ffffff00","curve":"stepped"},{"time":0.7667,"color":"ffffff00"},{"time":0.8,"color":"ffffffff"}]}},"bones":{"Wolf_body":{"rotate":[{"curve":[0.278,0,0.556,-0.68]},{"time":0.8333,"value":-0.68,"curve":[1.111,-0.68,1.389,0]},{"time":1.6667}],"translate":[{"curve":[0.278,0,0.556,0.03,0.278,0,0.556,0.95]},{"time":0.8333,"x":0.03,"y":0.95,"curve":[1.111,0.03,1.389,0,1.111,0.95,1.389,0]},{"time":1.6667}],"scale":[{"curve":[0.278,1,0.556,1.028,0.278,1,0.556,1]},{"time":0.8333,"x":1.028,"curve":[1.111,1.028,1.389,1,1.111,1,1.389,1]},{"time":1.6667}]},"Wolf_body2":{"rotate":[{"curve":[0.278,0,0.556,1.4]},{"time":0.8333,"value":1.4,"curve":[1.111,1.4,1.389,0]},{"time":1.6667}]},"Wolf_body3":{"rotate":[{"curve":[0.278,0,0.556,-1.95]},{"time":0.8333,"value":-1.95,"curve":[1.111,-1.95,1.389,0]},{"time":1.6667}]},"Wolf_arm_l":{"rotate":[{"value":-27.15,"curve":[0.278,-27.15,0.556,3.56]},{"time":0.8333,"value":3.56,"curve":[1.111,3.56,1.389,-27.15]},{"time":1.6667,"value":-27.15}]},"Wolf_arm_l2":{"rotate":[{"curve":[0.278,0,0.556,3.56]},{"time":0.8333,"value":3.56,"curve":[1.111,3.56,1.389,0]},{"time":1.6667}]},"Wolf_arm_l3":{"rotate":[{"curve":[0.278,0,0.556,3.56]},{"time":0.8333,"value":3.56,"curve":[1.111,3.56,1.389,0]},{"time":1.6667}]},"Wolf_bag":{"rotate":[{"curve":[0.144,0,0.289,-8.63]},{"time":0.4333,"value":-8.63,"curve":[0.567,-8.63,0.7,-2.43]},{"time":0.8333,"curve":[0.967,2.43,1.1,5.94]},{"time":1.2333,"value":5.94,"curve":[1.378,5.94,1.522,0]},{"time":1.6667}]},"Wolf_leg_r":{"rotate":[{"value":-18.11,"curve":[0.278,-18.11,0.556,26.61]},{"time":0.8333,"value":26.61,"curve":[1.111,26.61,1.389,-18.11]},{"time":1.6667,"value":-18.11}],"translate":[{"x":-7.23,"y":-14.68},{"time":0.8333,"x":4.69,"y":-22.09},{"time":1.6667,"x":-7.23,"y":-14.68}]},"Wolf_leg_r2":{"rotate":[{"curve":[0.201,0,0.402,-26.6]},{"time":0.6,"value":-27.88,"curve":[0.68,-28.37,0.756,-4.42]},{"time":0.8333,"value":-4.42,"curve":[1.111,-4.42,1.389,0]},{"time":1.6667}]},"Wolf_leg_r3":{"rotate":[{"curve":[0.278,0,0.556,1.68]},{"time":0.8333,"value":1.68,"curve":[1.111,1.68,1.389,0]},{"time":1.6667}]},"Wolf_leg_l":{"rotate":[{"value":22.89,"curve":[0.278,22.89,0.556,-20.27]},{"time":0.8333,"value":-20.27,"curve":[1.111,-20.27,1.389,22.89]},{"time":1.6667,"value":22.89}],"translate":[{"x":0.19,"y":13.69},{"time":0.8333,"x":-8.49,"y":23.29},{"time":1.6667,"x":0.19,"y":13.69}]},"Wolf_leg_l2":{"rotate":[{"curve":[0.278,0,0.556,-4.76]},{"time":0.8333,"value":-4.76,"curve":[1.023,-4.76,1.213,-33]},{"time":1.4,"value":-31.59,"curve":[1.491,-30.94,1.579,0]},{"time":1.6667}]},"Wolf_leg_l3":{"rotate":[{"curve":[0.278,0,0.556,3.81]},{"time":0.8333,"value":3.81,"curve":[1.111,3.81,1.389,0]},{"time":1.6667}]},"Wolf_tail":{"rotate":[{},{"time":0.8333,"value":-0.33},{"time":1.6667}]},"Wolf_tail2":{"rotate":[{},{"time":0.4333,"value":-7.44},{"time":0.8333,"value":-0.33},{"time":1.2333,"value":14.61},{"time":1.6667}]},"Wolf_tail3":{"rotate":[{},{"time":0.4333,"value":-7.44},{"time":0.8333,"value":-0.33},{"time":1.2333,"value":14.61},{"time":1.6667}]},"Wolf_tail4":{"rotate":[{},{"time":0.4333,"value":-7.44},{"time":0.8333,"value":-0.33},{"time":1.2333,"value":14.61},{"time":1.6667}]},"Wolf_tail5":{"rotate":[{},{"time":0.4333,"value":-7.44},{"time":0.8333,"value":-0.33},{"time":1.2333,"value":14.61},{"time":1.6667}]},"Wolf_tail6":{"rotate":[{},{"time":0.4333,"value":-7.44},{"time":0.8333,"value":-0.33},{"time":1.2333,"value":14.61},{"time":1.6667}]},"Wolf_deco":{"rotate":[{"curve":[0.278,0,0.556,-11.62]},{"time":0.8333,"value":-11.62,"curve":[1.111,-11.62,1.389,0]},{"time":1.6667}]},"Wolf_arm_r":{"rotate":[{"value":25.23,"curve":[0.278,25.23,0.556,-5.38]},{"time":0.8333,"value":-5.38,"curve":[1.111,-5.38,1.389,25.23]},{"time":1.6667,"value":25.23}]},"Wolf_arm_r2":{"rotate":[{"curve":[0.278,0,0.556,-5.38]},{"time":0.8333,"value":-5.38,"curve":[1.111,-5.38,1.389,0]},{"time":1.6667}]},"Wolf_arm_r3":{"rotate":[{"curve":[0.278,0,0.556,-5.38]},{"time":0.8333,"value":-5.38,"curve":[1.111,-5.38,1.389,0]},{"time":1.6667}]},"Wolf_head":{"rotate":[{"curve":[0.278,0,0.556,0.4]},{"time":0.8333,"value":0.4,"curve":[1.111,0.4,1.389,0]},{"time":1.6667}],"translate":[{"x":0.57,"y":0.01,"curve":[0.367,0.57,0.733,-1.56,0.367,0.01,0.733,-3.9]},{"time":1.1,"x":-1.56,"y":-3.9,"curve":[1.289,-1.56,1.478,0.57,1.289,-3.9,1.478,0.01]},{"time":1.6667,"x":0.57,"y":0.01}]},"Wolf_ear_r":{"rotate":[{"curve":[0.067,0,0.133,-5.12]},{"time":0.2,"value":-5.12,"curve":[0.244,-5.12,0.289,4.5]},{"time":0.3333,"value":4.5,"curve":[0.367,4.5,0.4,-2.87]},{"time":0.4333,"value":-2.87,"curve":[0.467,-2.87,0.5,7.34]},{"time":0.5333,"value":7.34,"curve":[0.556,7.34,0.578,-2.79]},{"time":0.6,"value":-2.79,"curve":[0.644,-2.79,0.689,6.25]},{"time":0.7333,"value":6.25,"curve":[0.767,6.25,0.8,3.18]},{"time":0.8333,"value":2.42,"curve":[0.933,0.12,1.033,-2.92]},{"time":1.1333,"value":-2.92,"curve":[1.233,-2.92,1.333,8.26]},{"time":1.4333,"value":8.26,"curve":[1.511,8.26,1.589,0]},{"time":1.6667}]},"Wolf_ear_l":{"rotate":[{"curve":[0.067,0,0.133,-7.67]},{"time":0.2,"value":-7.67,"curve":[0.222,-7.67,0.244,-2.17]},{"time":0.2667,"value":-2.17,"curve":[0.3,-2.17,0.333,-14.56]},{"time":0.3667,"value":-14.56,"curve":[0.4,-14.56,0.433,-3.65]},{"time":0.4667,"value":-3.65,"curve":[0.489,-3.65,0.511,-10.71]},{"time":0.5333,"value":-10.71,"curve":[0.567,-10.71,0.6,0.83]},{"time":0.6333,"value":0.83,"curve":[0.7,0.83,0.767,0.83]},{"time":0.8333,"curve":[0.889,-0.69,0.944,-10.66]},{"time":1,"value":-10.66,"curve":[1.089,-10.66,1.178,4.51]},{"time":1.2667,"value":4.51,"curve":[1.322,4.51,1.378,-15.22]},{"time":1.4333,"value":-15.22,"curve":[1.511,-15.22,1.589,0]},{"time":1.6667}]},"Wolf_head3":{"translate":[{},{"time":0.1,"x":-3.93,"y":6.06},{"time":0.2333,"x":-1.79,"y":2.25},{"time":0.4,"x":-3.39,"y":6.7},{"time":0.5667,"x":-2.6,"y":2.57},{"time":0.7333,"x":0.04,"y":0.22},{"time":0.9,"x":1.8,"y":1.42},{"time":1.0667,"x":3.14,"y":4.65},{"time":1.2333,"x":4.73,"y":1.69},{"time":1.4,"x":2.13,"y":4.06},{"time":1.5333,"x":5.28,"y":-2.22},{"time":1.6667}]},"Wolf_head4":{"translate":[{},{"time":0.1333,"x":-1.76,"y":-2.1},{"time":0.3,"x":-0.41,"y":-0.46},{"time":0.4667,"x":0.01,"y":-2.59},{"time":0.6333,"x":0.18,"y":0.03},{"time":0.8,"x":-1.05,"y":-2.48},{"time":1,"x":-0.91,"y":0.35},{"time":1.2,"x":-1.32,"y":-2.07},{"time":1.4,"x":-0.19,"y":2.14},{"time":1.6667}]},"Wolf_head2":{"translate":[{},{"time":0.3,"x":-3.75,"y":-1.65},{"time":0.4,"x":-0.09,"y":-0.47},{"time":0.5,"x":-5.58,"y":-1.84},{"time":0.6,"x":-0.26,"y":-2.62},{"time":0.7333,"x":-5.85,"y":-3.55},{"time":0.9,"x":-2.52,"y":-3.21},{"time":1.1667,"x":-6.06,"y":-5.34},{"time":1.3667,"x":-0.81,"y":-4.74},{"time":1.6667}]}}},"skill01":{"slots":{"weapon":{"rgba":[{"time":0.4667,"color":"ffffffff","curve":[0.5,1,0.533,1,0.5,1,0.533,1,0.5,1,0.533,1,0.5,1,0.533,0]},{"time":0.5667,"color":"ffffff00","curve":"stepped"},{"time":1.5333,"color":"ffffff00","curve":[1.578,1,1.622,1,1.578,1,1.622,1,1.578,1,1.622,1,1.578,0,1.622,1]},{"time":1.6667,"color":"ffffffff"}]},"Wolf_eye":{"rgba":[{"time":0.6667,"color":"ffffffff"},{"time":0.7,"color":"ffffff00","curve":"stepped"},{"time":0.7667,"color":"ffffff00"},{"time":0.8,"color":"ffffffff"}]}},"bones":{"weapon":{"rotate":[{"curve":[0.122,0,0.244,-67]},{"time":0.3667,"value":-67,"curve":[0.467,-67,0.567,-54.64]},{"time":0.6667,"value":-40.28,"curve":[0.722,-32.31,0.778,0]},{"time":0.8333,"curve":[1.067,0,1.3,0.19]},{"time":1.5333,"value":0.19,"curve":[1.556,0.19,1.578,0.2]},{"time":1.6,"value":0.15,"curve":[1.623,0.1,1.645,0]},{"time":1.6667}],"translate":[{"curve":[0.122,0,0.244,-31.34,0.122,0,0.244,-11.11]},{"time":0.3667,"x":-31.34,"y":-29.21,"curve":[0.467,-31.34,0.567,-31.34,0.467,-44.03,0.567,-49.04]},{"time":0.6667,"x":-15.49,"y":-98.76,"curve":[0.722,-6.69,0.778,414.17,0.722,-126.38,0.778,-261.24]},{"time":0.8333,"x":414.17,"y":-261.24,"curve":[1.067,414.17,1.3,0,1.067,-261.24,1.3,0]},{"time":1.5333}]},"Wolf_ear_l":{"rotate":[{"curve":[0.067,0,0.133,-7.67]},{"time":0.2,"value":-7.67,"curve":[0.222,-7.67,0.244,-2.17]},{"time":0.2667,"value":-2.17,"curve":[0.3,-2.17,0.333,-14.56]},{"time":0.3667,"value":-14.56,"curve":[0.4,-14.56,0.433,-3.65]},{"time":0.4667,"value":-3.65,"curve":[0.489,-3.65,0.511,-10.71]},{"time":0.5333,"value":-10.71,"curve":[0.567,-10.71,0.6,0.83]},{"time":0.6333,"value":0.83,"curve":[0.7,0.83,0.767,0.83]},{"time":0.8333,"curve":[0.889,-0.69,0.944,-10.66]},{"time":1,"value":-10.66,"curve":[1.089,-10.66,1.178,4.51]},{"time":1.2667,"value":4.51,"curve":[1.322,4.51,1.378,-15.22]},{"time":1.4333,"value":-15.22,"curve":[1.511,-15.22,1.589,0]},{"time":1.6667}]},"Wolf_ear_r":{"rotate":[{"curve":[0.067,0,0.133,-5.12]},{"time":0.2,"value":-5.12,"curve":[0.244,-5.12,0.289,4.5]},{"time":0.3333,"value":4.5,"curve":[0.367,4.5,0.4,-2.87]},{"time":0.4333,"value":-2.87,"curve":[0.467,-2.87,0.5,7.34]},{"time":0.5333,"value":7.34,"curve":[0.556,7.34,0.578,-2.79]},{"time":0.6,"value":-2.79,"curve":[0.644,-2.79,0.689,6.25]},{"time":0.7333,"value":6.25,"curve":[0.767,6.25,0.8,3.18]},{"time":0.8333,"value":2.42,"curve":[0.933,0.12,1.033,-2.92]},{"time":1.1333,"value":-2.92,"curve":[1.233,-2.92,1.333,8.26]},{"time":1.4333,"value":8.26,"curve":[1.511,8.26,1.589,0]},{"time":1.6667}]},"Wolf_arm_r3":{"rotate":[{"curve":[0.278,0,0.556,-5.38]},{"time":0.8333,"value":-5.38,"curve":[1.111,-5.38,1.389,0]},{"time":1.6667}]},"Wolf_arm_r2":{"rotate":[{"curve":[0.089,0,0.178,27.44]},{"time":0.2667,"value":26.69,"curve":[0.456,25.1,0.644,-5.38]},{"time":0.8333,"value":-5.38,"curve":[1.111,-5.38,1.389,0]},{"time":1.6667}]},"Wolf_arm_r":{"rotate":[{"curve":[0.089,0,0.178,22.71]},{"time":0.2667,"value":21.96,"curve":[0.456,20.37,0.644,-24.58]},{"time":0.8333,"value":-24.58,"curve":[1.111,-24.58,1.389,0]},{"time":1.6667}]},"Wolf_deco":{"rotate":[{"curve":[0.278,0,0.556,-11.62]},{"time":0.8333,"value":-11.62,"curve":[1.111,-11.62,1.389,0]},{"time":1.6667}]},"Wolf_leg_l3":{"rotate":[{"curve":[0.089,0,0.178,23.14]},{"time":0.2667,"value":23.67,"curve":[0.456,24.8,0.644,3.81]},{"time":0.8333,"value":3.81,"curve":[1.111,3.81,1.389,0]},{"time":1.6667}]},"Wolf_leg_l2":{"rotate":[{"curve":[0.089,0,0.178,-39.54]},{"time":0.2667,"value":-40.2,"curve":[0.333,-40.7,0.4,-58.63]},{"time":0.4667,"value":-52.89,"curve":[0.589,-42.38,0.711,-4.76]},{"time":0.8333,"value":-4.76,"curve":[1.111,-4.76,1.389,0]},{"time":1.6667}]},"Wolf_leg_l":{"rotate":[{"curve":[0.089,0,0.178,10.44]},{"time":0.2667,"value":12.35,"curve":[0.333,13.78,0.4,46.04]},{"time":0.4667,"value":46.2,"curve":[0.589,46.49,0.711,13.68]},{"time":0.8333,"value":13.68,"curve":[1.111,13.68,1.389,0]},{"time":1.6667}]},"Wolf_leg_r3":{"rotate":[{"curve":[0.089,0,0.178,26.25]},{"time":0.2667,"value":26.49,"curve":[0.333,26.66,0.4,5.11]},{"time":0.4667,"value":1.1,"curve":[0.589,-6.25,0.711,1.68]},{"time":0.8333,"value":1.68,"curve":[1.111,1.68,1.389,0]},{"time":1.6667}]},"Wolf_leg_r2":{"rotate":[{"curve":[0.089,0,0.178,-51.12]},{"time":0.2667,"value":-51.74,"curve":[0.333,-52.2,0.4,-61.34]},{"time":0.4667,"value":-53.68,"curve":[0.589,-39.66,0.711,-4.42]},{"time":0.8333,"value":-4.42,"curve":[1.111,-4.42,1.389,0]},{"time":1.6667}]},"Wolf_leg_r":{"rotate":[{"curve":[0.07,0,0.166,12.64]},{"time":0.2667,"value":12.24,"curve":[0.333,11.98,0.403,17.5]},{"time":0.4667,"value":15.86,"curve":[0.654,11.28,0.816,-3.39]},{"time":0.8333,"value":-3.39,"curve":[1.111,-3.39,1.389,0]},{"time":1.6667}]},"Wolf_bag":{"rotate":[{"curve":[0.144,0,0.289,-8.63]},{"time":0.4333,"value":-8.63,"curve":[0.567,-8.63,0.7,-2.43]},{"time":0.8333,"curve":[0.967,2.43,1.1,5.94]},{"time":1.2333,"value":5.94,"curve":[1.378,5.94,1.522,0]},{"time":1.6667}]},"Wolf_arm_l3":{"rotate":[{"curve":[0.278,0,0.556,3.56]},{"time":0.8333,"value":3.56,"curve":[1.111,3.56,1.389,0]},{"time":1.6667}]},"Wolf_arm_l2":{"rotate":[{"curve":[0.278,0,0.556,3.56]},{"time":0.8333,"value":3.56,"curve":[1.111,3.56,1.389,0]},{"time":1.6667}]},"Wolf_arm_l":{"rotate":[{"curve":[0.089,0,0.178,202.92]},{"time":0.2667,"value":203.42,"curve":[0.333,203.79,0.4,193.66]},{"time":0.4667,"value":153.54,"curve":[0.589,80.13,0.711,-53.23]},{"time":0.8333,"value":-53.23,"curve":[1.056,-53.23,1.28,-19.11]},{"time":1.5,"value":-5.6,"curve":[1.557,-2.29,1.612,0]},{"time":1.6667}]},"Wolf_body3":{"rotate":[{"curve":[0.089,0,0.178,4.08]},{"time":0.2667,"value":3.81,"curve":[0.456,3.23,0.644,-1.95]},{"time":0.8333,"value":-1.95,"curve":[0.9,-1.95,0.967,0.72]},{"time":1.0333,"value":0.89,"curve":[1.244,1.43,1.456,0]},{"time":1.6667}]},"Wolf_body2":{"rotate":[{"curve":[0.089,0,0.178,11.58]},{"time":0.2667,"value":11.77,"curve":[0.456,12.18,0.644,1.4]},{"time":0.8333,"value":1.4,"curve":[0.9,1.4,0.967,3.96]},{"time":1.0333,"value":3.83,"curve":[1.244,3.45,1.456,0]},{"time":1.6667}]},"Wolf_body":{"rotate":[{"curve":[0.089,0,0.178,3.03]},{"time":0.2667,"value":2.94,"curve":[0.456,2.74,0.644,-0.68]},{"time":0.8333,"value":-0.68,"curve":[0.9,-0.68,1.456,0]},{"time":1.6667}],"translate":[{"curve":[0.089,0,0.178,-0.9,0.089,0,0.178,-18.03]},{"time":0.2667,"x":-0.9,"y":-17.9,"curve":[0.356,-0.9,0.445,0.97,0.356,-17.77,0.445,82.29]},{"time":0.5333,"x":1.19,"y":86.71,"curve":[0.634,1.43,0.734,0.03,0.634,91.62,0.734,0.95]},{"time":0.8333,"x":0.03,"y":0.95,"curve":[1.111,0.03,1.389,0,1.111,0.95,1.389,0]},{"time":1.6667}],"scale":[{"curve":[0.278,1,0.556,1.028,0.278,1,0.556,1]},{"time":0.8333,"x":1.028,"curve":[1.111,1.028,1.389,1,1.111,1,1.389,1]},{"time":1.6667}]},"Wolf_head3":{"translate":[{},{"time":0.1,"x":-3.93,"y":6.06},{"time":0.2333,"x":-1.79,"y":2.25},{"time":0.4,"x":-3.39,"y":6.7},{"time":0.5667,"x":-2.6,"y":2.57},{"time":0.7333,"x":0.04,"y":0.22},{"time":0.9,"x":1.8,"y":1.42},{"time":1.0667,"x":3.14,"y":4.65},{"time":1.2333,"x":4.73,"y":1.69},{"time":1.4,"x":2.13,"y":4.06},{"time":1.5333,"x":5.28,"y":-2.22},{"time":1.6667}]},"Wolf_head4":{"translate":[{},{"time":0.1333,"x":-1.76,"y":-2.1},{"time":0.3,"x":-0.41,"y":-0.46},{"time":0.4667,"x":0.01,"y":-2.59},{"time":0.6333,"x":0.18,"y":0.03},{"time":0.8,"x":-1.05,"y":-2.48},{"time":1,"x":-0.91,"y":0.35},{"time":1.2,"x":-1.32,"y":-2.07},{"time":1.4,"x":-0.19,"y":2.14},{"time":1.6667}]},"Wolf_head2":{"translate":[{},{"time":0.3,"x":-3.75,"y":-1.65},{"time":0.4,"x":-0.09,"y":-0.47},{"time":0.5,"x":-5.58,"y":-1.84},{"time":0.6,"x":-0.26,"y":-2.62},{"time":0.7333,"x":-5.85,"y":-3.55},{"time":0.9,"x":-2.52,"y":-3.21},{"time":1.1667,"x":-6.06,"y":-5.34},{"time":1.3667,"x":-0.81,"y":-4.74},{"time":1.6667}]},"Wolf_tail":{"rotate":[{},{"time":0.8333,"value":-0.33},{"time":1.6667}]},"Wolf_tail2":{"rotate":[{},{"time":0.4333,"value":-7.44},{"time":0.8333,"value":-0.33},{"time":1.2333,"value":14.61},{"time":1.6667}]},"Wolf_tail3":{"rotate":[{},{"time":0.4333,"value":-7.44},{"time":0.8333,"value":-0.33},{"time":1.2333,"value":14.61},{"time":1.6667}]},"Wolf_tail4":{"rotate":[{},{"time":0.4333,"value":-7.44},{"time":0.8333,"value":-0.33},{"time":1.2333,"value":14.61},{"time":1.6667}]},"Wolf_tail5":{"rotate":[{},{"time":0.4333,"value":-7.44},{"time":0.8333,"value":-0.33},{"time":1.2333,"value":14.61},{"time":1.6667}]},"Wolf_tail6":{"rotate":[{},{"time":0.4333,"value":-7.44},{"time":0.8333,"value":-0.33},{"time":1.2333,"value":14.61},{"time":1.6667}]},"Wolf_head":{"rotate":[{},{"time":0.2667,"value":-4.63},{"time":0.8333,"value":-3.32},{"time":1.6667}],"translate":[{},{"time":1,"x":-3.8,"y":-21.19},{"time":1.6667}]}},"events":[{"time":0.5667,"name":"event_attack"}]}}}